quadraturerules/__init__.py
quadraturerules/domain.py
quadraturerules/py.typed
quadraturerules/rules/__init__.py
quadraturerules/rules/centroid_quadrature.py
quadraturerules/rules/closed_newton_cotes.py
quadraturerules/rules/gauss_legendre.py
quadraturerules/rules/gauss_lobatto_legendre.py
quadraturerules/rules/hammer_marlowe_stroud.py
quadraturerules/rules/open_newton_cotes.py
quadraturerules/rules/sauter_schwab.py
quadraturerules/rules/vertex_quadrature.py
quadraturerules/rules/xiao_gimbutas.py
quadraturerules-0.9.0.dist-info/licenses/LICENSE
quadraturerules-0.9.0.dist-info/METADATA
quadraturerules-0.9.0.dist-info/WHEEL
quadraturerules-0.9.0.dist-info/top_level.txt
quadraturerules-0.9.0.dist-info/RECORD
