Metadata-Version: 2.4
Name: quadraturerules
Version: 0.9.0
Summary: quadrature rules library
Author-email: Matthew Scroggs <quadraturerules@mscroggs.co.uk>
License: MIT License
Project-URL: homepage, https://quadraturerules.org
Project-URL: repository, https://github.com/quadraturerules/quadraturerules
Requires-Python: >=3.10.0
License-File: LICENSE
Requires-Dist: numpy
Provides-Extra: style
Requires-Dist: ruff; extra == "style"
Requires-Dist: mypy; extra == "style"
Provides-Extra: test
Requires-Dist: pytest; extra == "test"
Provides-Extra: ci
Requires-Dist: quadraturerules[test]; extra == "ci"
Requires-Dist: quadraturerules[style]; extra == "ci"
Dynamic: license-file
